[
  {
    "id": 202979,
    "createdAt": "2021-03-30 17:18:05.475",
    "updatedAt": "2021-03-30 17:19:29.956",
    "handle": 202979,
    "name": "Jamie Young",
    "type": "Assistant Coach",
    "isAssistant": 2,
    "teamId": 1610612738
  },
  {
    "id": 1627329,
    "createdAt": "2021-03-30 17:18:05.477",
    "updatedAt": "2021-03-30 17:19:29.982",
    "handle": 1627329,
    "name": "Scott Morrison",
    "type": "Assistant Coach",
    "isAssistant": 2,
    "teamId": 1610612738
  },
  {
    "id": 1628210,
    "createdAt": "2021-03-30 17:18:05.479",
    "updatedAt": "2021-03-30 17:19:29.996",
    "handle": 1628210,
    "name": "Joe Mazzulla",
    "type": "Assistant Coach",
    "isAssistant": 2,
    "teamId": 1610612738
  },
  {
    "id": 1628765,
    "createdAt": "2021-03-30 17:18:05.482",
    "updatedAt": "2021-03-30 17:19:30.028",
    "handle": 1628765,
    "name": "Art Horne",
    "type": "Trainer",
    "isAssistant": 3,
    "teamId": 1610612738
  },
  {
    "id": 959,
    "createdAt": "2021-03-30 17:18:05.484",
    "updatedAt": "2021-03-30 17:19:30.247",
    "handle": 959,
    "name": "Steve Nash",
    "type": "Head Coach",
    "isAssistant": 1,
    "teamId": 1610612751
  },
  {
    "id": 202588,
    "createdAt": "2021-03-30 17:18:05.486",
    "updatedAt": "2021-03-30 17:19:30.253",
    "handle": 202588,
    "name": "Jacque Vaughn",
    "type": "Lead Assistant Coach",
    "isAssistant": 13,
    "teamId": 1610612751
  },
  {
    "id": 1783,
    "createdAt": "2021-03-30 17:18:05.488",
    "updatedAt": "2021-03-30 17:19:30.278",
    "handle": 1783,
    "name": "Mike D'Antoni",
    "type": "Assistant Coach",
    "isAssistant": 2,
    "teamId": 1610612751
  },
  {
    "id": 203152,
    "createdAt": "2021-03-30 17:18:05.49",
    "updatedAt": "2021-03-30 17:19:30.287",
    "handle": 203152,
    "name": "Ime Udoka",
    "type": "Assistant Coach",
    "isAssistant": 2,
    "teamId": 1610612751
  },
  {
    "id": 1627876,
    "createdAt": "2021-03-30 17:18:05.492",
    "updatedAt": "2021-03-30 17:19:30.3",
    "handle": 1627876,
    "name": "Adam Harrington",
    "type": "Assistant Coach",
    "isAssistant": 2,
    "teamId": 1610612751
  },
  {
    "id": 202435,
    "createdAt": "2021-03-30 17:18:05.494",
    "updatedAt": "2021-03-30 17:19:30.608",
    "handle": 202435,
    "name": "James Borrego",
    "type": "Head Coach",
    "isAssistant": 1,
    "teamId": 1610612766
  },
  {
    "id": 2472,
    "createdAt": "2021-03-30 17:18:05.498",
    "updatedAt": "2021-03-30 17:19:30.639",
    "handle": 2472,
    "name": "Jay Triano",
    "type": "Assistant Coach",
    "isAssistant": 2,
    "teamId": 1610612766
  },
  {
    "id": 202602,
    "createdAt": "2021-03-30 17:18:05.5",
    "updatedAt": "2021-03-30 17:19:30.647",
    "handle": 202602,
    "name": "Chad Iske",
    "type": "Assistant Coach",
    "isAssistant": 2,
    "teamId": 1610612766
  },
  {
    "id": 101278,
    "createdAt": "2021-03-30 17:18:05.501",
    "updatedAt": "2021-03-30 17:19:30.654",
    "handle": 101278,
    "name": "Joe Sharpe",
    "type": "Trainer",
    "isAssistant": 3,
    "teamId": 1610612766
  },
  {
    "id": 201666,
    "createdAt": "2021-03-30 17:18:05.503",
    "updatedAt": "2021-03-30 17:19:30.681",
    "handle": 201666,
    "name": "Dennis Williams",
    "type": "Assistant Trainer",
    "isAssistant": 4,
    "teamId": 1610612766
  },
  {
    "id": 1627310,
    "createdAt": "2021-03-30 17:18:05.505",
    "updatedAt": "2021-03-30 17:19:30.894",
    "handle": 1627310,
    "name": "Billy Donovan",
    "type": "Head Coach",
    "isAssistant": 1,
    "teamId": 1610612741
  },
  {
    "id": 1627604,
    "createdAt": "2021-03-30 17:18:05.523",
    "updatedAt": "2021-03-30 17:19:30.902",
    "handle": 1627604,
    "name": "Chris Fleming",
    "type": "Assistant Coach",
    "isAssistant": 2,
    "teamId": 1610612741
  },
  {
    "id": 2511,
    "createdAt": "2021-03-30 17:18:05.525",
    "updatedAt": "2021-03-30 17:19:30.926",
    "handle": 2511,
    "name": "Mike Wilhelm",
    "type": "Assistant Coach",
    "isAssistant": 2,
    "teamId": 1610612741
  },
  {
    "id": 204031,
    "createdAt": "2021-03-30 17:18:05.527",
    "updatedAt": "2021-03-30 17:19:30.943",
    "handle": 204031,
    "name": "Joshua Longstaff",
    "type": "Assistant Coach",
    "isAssistant": 2,
    "teamId": 1610612741
  },
  {
    "id": 1312,
    "createdAt": "2021-03-30 17:18:05.529",
    "updatedAt": "2021-03-30 17:19:30.951",
    "handle": 1312,
    "name": "Maurice Cheeks",
    "type": "Assistant Coach",
    "isAssistant": 2,
    "teamId": 1610612741
  },
  {
    "id": 2394,
    "createdAt": "2021-03-30 17:18:05.531",
    "updatedAt": "2021-03-30 17:19:30.957",
    "handle": 2394,
    "name": "Pete Myers",
    "type": "Assistant Coach",
    "isAssistant": 2,
    "teamId": 1610612741
  },
  {
    "id": 1629710,
    "createdAt": "2021-03-30 17:18:05.533",
    "updatedAt": "2021-03-30 17:19:31.194",
    "handle": 1629710,
    "name": "Lindsay Gottlieb",
    "type": "Assistant Coach",
    "isAssistant": 2,
    "teamId": 1610612739
  },
  {
    "id": 204238,
    "createdAt": "2021-03-30 17:18:05.534",
    "updatedAt": "2021-03-30 17:19:31.207",
    "handle": 204238,
    "name": "Antonio Lang",
    "type": "Assistant Coach",
    "isAssistant": 2,
    "teamId": 1610612739
  },
  {
    "id": 1629110,
    "createdAt": "2021-03-30 17:18:05.536",
    "updatedAt": "2021-03-30 17:19:31.234",
    "handle": 1629110,
    "name": "Dan Geriot",
    "type": "Assistant Coach",
    "isAssistant": 2,
    "teamId": 1610612739
  },
  {
    "id": 204286,
    "createdAt": "2021-03-30 17:18:05.54",
    "updatedAt": "2021-03-30 17:19:31.248",
    "handle": 204286,
    "name": "Stephen Spiro",
    "type": "Trainer",
    "isAssistant": 3,
    "teamId": 1610612739
  },
  {
    "id": 1320,
    "createdAt": "2021-03-30 17:18:05.542",
    "updatedAt": "2021-03-30 17:19:31.478",
    "handle": 1320,
    "name": "Rick Carlisle",
    "type": "Head Coach",
    "isAssistant": 1,
    "teamId": 1610612742
  },
  {
    "id": 1628785,
    "createdAt": "2021-03-30 17:18:05.677",
    "updatedAt": "2021-03-30 17:19:31.486",
    "handle": 1628785,
    "name": "Zach Guthrie",
    "type": "Assistant Coach",
    "isAssistant": 2,
    "teamId": 1610612742
  },
  {
    "id": 202427,
    "createdAt": "2021-03-30 17:18:05.544",
    "updatedAt": "2021-03-30 17:19:31.493",
    "handle": 202427,
    "name": "Jamahl Mosley",
    "type": "Assistant Coach",
    "isAssistant": 2,
    "teamId": 1610612742
  },
  {
    "id": 2868,
    "createdAt": "2021-03-30 17:18:05.548",
    "updatedAt": "2021-03-30 17:19:31.534",
    "handle": 2868,
    "name": "Casey Smith",
    "type": "Trainer",
    "isAssistant": 3,
    "teamId": 1610612742
  },
  {
    "id": 2871,
    "createdAt": "2021-03-30 17:18:05.549",
    "updatedAt": "2021-03-30 17:19:31.541",
    "handle": 2871,
    "name": "Dionne Calhoun",
    "type": "Assistant Trainer",
    "isAssistant": 4,
    "teamId": 1610612742
  },
  {
    "id": 2610,
    "createdAt": "2021-03-30 17:18:05.551",
    "updatedAt": "2021-03-30 17:19:31.751",
    "handle": 2610,
    "name": "Michael Malone",
    "type": "Head Coach",
    "isAssistant": 1,
    "teamId": 1610612743
  },
  {
    "id": 203391,
    "createdAt": "2021-03-30 17:18:05.553",
    "updatedAt": "2021-03-30 17:19:31.758",
    "handle": 203391,
    "name": "Ryan Bowen",
    "type": "Assistant Coach",
    "isAssistant": 2,
    "teamId": 1610612743
  },
  {
    "id": 202894,
    "createdAt": "2021-03-30 17:18:05.555",
    "updatedAt": "2021-03-30 17:19:31.782",
    "handle": 202894,
    "name": "Charles Klask",
    "type": "Assistant Coach",
    "isAssistant": 2,
    "teamId": 1610612743
  },
  {
    "id": 203165,
    "createdAt": "2021-03-30 17:18:05.573",
    "updatedAt": "2021-03-30 17:19:31.789",
    "handle": 203165,
    "name": "Bob Weiss",
    "type": "Assistant Coach",
    "isAssistant": 2,
    "teamId": 1610612743
  },
  {
    "id": 203759,
    "createdAt": "2021-03-30 17:18:05.577",
    "updatedAt": "2021-03-30 17:19:31.802",
    "handle": 203759,
    "name": "Jordi Fernandez",
    "type": "Assistant Coach",
    "isAssistant": 2,
    "teamId": 1610612743
  },
  {
    "id": 1018,
    "createdAt": "2021-03-30 17:18:05.579",
    "updatedAt": "2021-03-30 17:19:31.808",
    "handle": 1018,
    "name": "Wes Unseld",
    "type": "Assistant Coach",
    "isAssistant": 2,
    "teamId": 1610612743
  },
  {
    "id": 1627167,
    "createdAt": "2021-03-30 17:18:05.581",
    "updatedAt": "2021-03-30 17:19:31.831",
    "handle": 1627167,
    "name": "Dan Shimensky",
    "type": "Trainer",
    "isAssistant": 3,
    "teamId": 1610612743
  },
  {
    "id": 204230,
    "createdAt": "2021-03-30 17:18:05.583",
    "updatedAt": "2021-03-30 17:19:32.048",
    "handle": 204230,
    "name": "Tim Hardaway",
    "type": "Assistant Coach",
    "isAssistant": 2,
    "teamId": 1610612765
  },
  {
    "id": 1336,
    "createdAt": "2021-03-30 17:18:05.584",
    "updatedAt": "2021-03-30 17:19:32.054",
    "handle": 1336,
    "name": "Tim Grgurich",
    "type": "Assistant Coach",
    "isAssistant": 2,
    "teamId": 1610612765
  },
  {
    "id": 202101,
    "createdAt": "2021-03-30 17:18:05.586",
    "updatedAt": "2021-03-30 17:19:32.078",
    "handle": 202101,
    "name": "Micah Nori",
    "type": "Assistant Coach",
    "isAssistant": 2,
    "teamId": 1610612765
  },
  {
    "id": 1226,
    "createdAt": "2021-03-30 17:18:05.591",
    "updatedAt": "2021-03-30 17:19:32.093",
    "handle": 1226,
    "name": "Sidney Lowe",
    "type": "Assistant Coach",
    "isAssistant": 2,
    "teamId": 1610612765
  },
  {
    "id": 201678,
    "createdAt": "2021-03-30 17:18:05.592",
    "updatedAt": "2021-03-30 17:19:32.099",
    "handle": 201678,
    "name": "Jim Scholler",
    "type": "Trainer",
    "isAssistant": 3,
    "teamId": 1610612765
  },
  {
    "id": 204239,
    "createdAt": "2021-03-30 17:18:05.594",
    "updatedAt": "2021-03-30 17:19:32.303",
    "handle": 204239,
    "name": "Jarron Collins",
    "type": "Assistant Coach",
    "isAssistant": 2,
    "teamId": 1610612744
  },
  {
    "id": 1658,
    "createdAt": "2021-03-30 17:18:05.596",
    "updatedAt": "2021-03-30 17:19:32.327",
    "handle": 1658,
    "name": "Mike Brown",
    "type": "Assistant Coach",
    "isAssistant": 2,
    "teamId": 1610612744
  },
  {
    "id": 204260,
    "createdAt": "2021-03-30 17:18:05.598",
    "updatedAt": "2021-03-30 17:19:32.337",
    "handle": 204260,
    "name": "Bruce Fraser",
    "type": "Assistant Coach",
    "isAssistant": 2,
    "teamId": 1610612744
  },
  {
    "id": 1796,
    "createdAt": "2021-03-30 17:18:05.6",
    "updatedAt": "2021-03-30 17:19:32.344",
    "handle": 1796,
    "name": "Ron Adams",
    "type": "Assistant Coach",
    "isAssistant": 2,
    "teamId": 1610612744
  },
  {
    "id": 2152,
    "createdAt": "2021-03-30 17:18:05.603",
    "updatedAt": "2021-03-30 17:19:32.577",
    "handle": 2152,
    "name": "Stephen Silas",
    "type": "Head Coach",
    "isAssistant": 1,
    "teamId": 1610612745
  },
  {
    "id": 1786,
    "createdAt": "2021-03-30 17:18:05.622",
    "updatedAt": "2021-03-30 17:19:32.592",
    "handle": 1786,
    "name": "John Lucas",
    "type": "Assistant Coach",
    "isAssistant": 2,
    "teamId": 1610612745
  },
  {
    "id": 201765,
    "createdAt": "2021-03-30 17:18:05.679",
    "updatedAt": "2021-03-30 17:19:32.836",
    "handle": 201765,
    "name": "Nate Bjorkgren",
    "type": "Head Coach",
    "isAssistant": 1,
    "teamId": 1610612754
  },
  {
    "id": 201696,
    "createdAt": "2021-03-30 17:18:05.681",
    "updatedAt": "2021-03-30 17:19:32.85",
    "handle": 201696,
    "name": "Kaleb Canales",
    "type": "Assistant Coach",
    "isAssistant": 2,
    "teamId": 1610612754
  },
  {
    "id": 101200,
    "createdAt": "2021-03-30 17:18:05.683",
    "updatedAt": "2021-03-30 17:19:32.89",
    "handle": 101200,
    "name": "Josh Corbeil",
    "type": "Trainer",
    "isAssistant": 3,
    "teamId": 1610612754
  },
  {
    "id": 201675,
    "createdAt": "2021-03-30 17:18:05.625",
    "updatedAt": "2021-03-30 17:19:32.897",
    "handle": 201675,
    "name": "Carl Eaton",
    "type": "Assistant Trainer",
    "isAssistant": 4,
    "teamId": 1610612754
  },
  {
    "id": 202978,
    "createdAt": "2021-03-30 17:18:05.627",
    "updatedAt": "2021-03-30 17:19:33.079",
    "handle": 202978,
    "name": "Tyronn Lue",
    "type": "Head Coach",
    "isAssistant": 1,
    "teamId": 1610612746
  },
  {
    "id": 2345,
    "createdAt": "2021-03-30 17:18:05.687",
    "updatedAt": "2021-03-30 17:19:33.352",
    "handle": 2345,
    "name": "Frank Vogel",
    "type": "Head Coach",
    "isAssistant": 1,
    "teamId": 1610612747
  },
  {
    "id": 1629748,
    "createdAt": "2021-03-30 17:18:05.689",
    "updatedAt": "2021-03-30 17:19:33.358",
    "handle": 1629748,
    "name": "Quinton Crawford",
    "type": "Assistant Coach",
    "isAssistant": 2,
    "teamId": 1610612747
  },
  {
    "id": 1353,
    "createdAt": "2021-03-30 17:18:05.691",
    "updatedAt": "2021-03-30 17:19:33.381",
    "handle": 1353,
    "name": "Lionel Hollins",
    "type": "Assistant Coach",
    "isAssistant": 2,
    "teamId": 1610612747
  },
  {
    "id": 203456,
    "createdAt": "2021-03-30 17:18:05.693",
    "updatedAt": "2021-03-30 17:19:33.388",
    "handle": 203456,
    "name": "Jason Kidd",
    "type": "Assistant Coach",
    "isAssistant": 2,
    "teamId": 1610612747
  },
  {
    "id": 203597,
    "createdAt": "2021-03-30 17:18:05.695",
    "updatedAt": "2021-03-30 17:19:33.395",
    "handle": 203597,
    "name": "Phil Handy",
    "type": "Assistant Coach",
    "isAssistant": 2,
    "teamId": 1610612747
  },
  {
    "id": 203624,
    "createdAt": "2021-03-30 17:18:05.699",
    "updatedAt": "2021-03-30 17:19:33.631",
    "handle": 203624,
    "name": "Taylor Jenkins",
    "type": "Head Coach",
    "isAssistant": 1,
    "teamId": 1610612763
  },
  {
    "id": 2086,
    "createdAt": "2021-03-30 17:18:05.701",
    "updatedAt": "2021-03-30 17:19:33.651",
    "handle": 2086,
    "name": "Scoonie Penn",
    "type": "Assistant Coach",
    "isAssistant": 2,
    "teamId": 1610612763
  },
  {
    "id": 1628234,
    "createdAt": "2021-03-30 17:18:05.703",
    "updatedAt": "2021-03-30 17:19:33.69",
    "handle": 1628234,
    "name": "David McClure",
    "type": "Assistant Coach",
    "isAssistant": 2,
    "teamId": 1610612763
  },
  {
    "id": 1630018,
    "createdAt": "2021-03-30 17:18:05.705",
    "updatedAt": "2021-03-30 17:19:33.704",
    "handle": 1630018,
    "name": "Eric Oetter",
    "type": "Trainer",
    "isAssistant": 3,
    "teamId": 1610612763
  },
  {
    "id": 1787,
    "createdAt": "2021-03-30 17:18:05.723",
    "updatedAt": "2021-03-30 17:19:33.892",
    "handle": 1787,
    "name": "Erik Spoelstra",
    "type": "Head Coach",
    "isAssistant": 1,
    "teamId": 1610612748
  },
  {
    "id": 2630,
    "createdAt": "2021-03-30 17:18:05.629",
    "updatedAt": "2021-03-30 17:19:34.652",
    "handle": 2630,
    "name": "Bob Beyer",
    "type": "Assistant Coach",
    "isAssistant": 2,
    "teamId": 1610612740
  },
  {
    "id": 1629450,
    "createdAt": "2021-03-30 17:18:05.633",
    "updatedAt": "2021-03-30 17:19:34.951",
    "handle": 1629450,
    "name": "Larry Greer",
    "type": "Assistant Coach",
    "isAssistant": 2,
    "teamId": 1610612752
  },
  {
    "id": 1370,
    "createdAt": "2021-03-30 17:18:05.635",
    "updatedAt": "2021-03-30 17:19:34.989",
    "handle": 1370,
    "name": "Roger Hinds",
    "type": "Trainer",
    "isAssistant": 3,
    "teamId": 1610612752
  },
  {
    "id": 1629758,
    "createdAt": "2021-03-30 17:18:05.636",
    "updatedAt": "2021-03-30 17:19:35.192",
    "handle": 1629758,
    "name": "Dave Bliss",
    "type": "Assistant Coach",
    "isAssistant": 2,
    "teamId": 1610612760
  },
  {
    "id": 203758,
    "createdAt": "2021-03-30 17:18:05.638",
    "updatedAt": "2021-03-30 17:19:35.199",
    "handle": 203758,
    "name": "Mike Miller",
    "type": "Assistant Coach",
    "isAssistant": 2,
    "teamId": 1610612760
  },
  {
    "id": 2366,
    "createdAt": "2021-03-30 17:18:05.641",
    "updatedAt": "2021-03-30 17:19:35.206",
    "handle": 2366,
    "name": "Mike Wilks",
    "type": "Assistant Coach",
    "isAssistant": 2,
    "teamId": 1610612760
  },
  {
    "id": 202859,
    "createdAt": "2021-03-30 17:18:05.642",
    "updatedAt": "2021-03-30 17:19:35.239",
    "handle": 202859,
    "name": "David Akinyooye",
    "type": "Assistant Coach",
    "isAssistant": 2,
    "teamId": 1610612760
  },
  {
    "id": 204013,
    "createdAt": "2021-03-30 17:18:05.644",
    "updatedAt": "2021-03-30 17:19:35.483",
    "handle": 204013,
    "name": "Pat Delany",
    "type": "Assistant Coach",
    "isAssistant": 2,
    "teamId": 1610612753
  },
  {
    "id": 1629427,
    "createdAt": "2021-03-30 17:18:05.648",
    "updatedAt": "2021-03-30 17:19:35.977",
    "handle": 1629427,
    "name": "Brian Randle",
    "type": "Assistant Coach",
    "isAssistant": 2,
    "teamId": 1610612756
  },
  {
    "id": 1865,
    "createdAt": "2021-03-30 17:18:05.65",
    "updatedAt": "2021-03-30 17:19:35.985",
    "handle": 1865,
    "name": "Randy Ayers",
    "type": "Assistant Coach",
    "isAssistant": 2,
    "teamId": 1610612756
  },
  {
    "id": 201046,
    "createdAt": "2021-03-30 17:18:05.652",
    "updatedAt": "2021-03-30 17:19:36.501",
    "handle": 201046,
    "name": "Lindsey Harding",
    "type": "Assistant Coach",
    "isAssistant": 2,
    "teamId": 1610612758
  },
  {
    "id": 1627564,
    "createdAt": "2021-03-30 17:18:05.654",
    "updatedAt": "2021-03-30 17:19:36.531",
    "handle": 1627564,
    "name": "Jonah Herscu",
    "type": "Assistant Coach",
    "isAssistant": 2,
    "teamId": 1610612758
  },
  {
    "id": 1628770,
    "createdAt": "2021-03-30 17:18:05.891",
    "updatedAt": "2021-03-30 17:19:29.681",
    "handle": 1628770,
    "name": "Matt Hill",
    "type": "Assistant Coach",
    "isAssistant": 2,
    "teamId": 1610612737
  },
  {
    "id": 1831,
    "createdAt": "2021-03-30 17:18:05.893",
    "updatedAt": "2021-03-30 17:19:29.689",
    "handle": 1831,
    "name": "Marlon Garnett",
    "type": "Assistant Coach",
    "isAssistant": 2,
    "teamId": 1610612737
  },
  {
    "id": 1628764,
    "createdAt": "2021-03-30 17:18:05.895",
    "updatedAt": "2021-03-30 17:19:29.697",
    "handle": 1628764,
    "name": "Scottie Parker",
    "type": "Trainer",
    "isAssistant": 3,
    "teamId": 1610612737
  },
  {
    "id": 1627877,
    "createdAt": "2021-03-30 17:18:05.897",
    "updatedAt": "2021-03-30 17:19:30.327",
    "handle": 1627877,
    "name": "Jordan Ott",
    "type": "Assistant Coach",
    "isAssistant": 2,
    "teamId": 1610612751
  },
  {
    "id": 1628803,
    "createdAt": "2021-03-30 17:18:05.899",
    "updatedAt": "2021-03-30 17:19:30.343",
    "handle": 1628803,
    "name": "Ryan Forehan-Kelly",
    "type": "Assistant Coach",
    "isAssistant": 2,
    "teamId": 1610612751
  },
  {
    "id": 203550,
    "createdAt": "2021-03-30 17:18:05.903",
    "updatedAt": "2021-03-30 17:19:30.377",
    "handle": 203550,
    "name": "Sebastien Poirier",
    "type": "Trainer",
    "isAssistant": 3,
    "teamId": 1610612751
  },
  {
    "id": 203811,
    "createdAt": "2021-03-30 17:18:05.922",
    "updatedAt": "2021-03-30 17:19:31.201",
    "handle": 203811,
    "name": "Greg Buckner",
    "type": "Assistant Coach",
    "isAssistant": 2,
    "teamId": 1610612739
  },
  {
    "id": 1628227,
    "createdAt": "2021-03-30 17:18:05.925",
    "updatedAt": "2021-03-30 17:19:32.358",
    "handle": 1628227,
    "name": "Drew Yoder",
    "type": "Trainer",
    "isAssistant": 3,
    "teamId": 1610612744
  },
  {
    "id": 1630277,
    "createdAt": "2021-03-30 17:18:05.927",
    "updatedAt": "2021-03-30 17:19:32.585",
    "handle": 1630277,
    "name": "Rick Higgins",
    "type": "Assistant Coach",
    "isAssistant": 2,
    "teamId": 1610612745
  },
  {
    "id": 202898,
    "createdAt": "2021-03-30 17:18:05.929",
    "updatedAt": "2021-03-30 17:19:32.606",
    "handle": 202898,
    "name": "Jeff Hornacek",
    "type": "Assistant Coach",
    "isAssistant": 2,
    "teamId": 1610612745
  },
  {
    "id": 1627657,
    "createdAt": "2021-03-30 17:18:05.931",
    "updatedAt": "2021-03-30 17:19:32.631",
    "handle": 1627657,
    "name": "Will Weaver",
    "type": "Assistant Coach",
    "isAssistant": 2,
    "teamId": 1610612745
  },
  {
    "id": 1257,
    "createdAt": "2021-03-30 17:18:05.932",
    "updatedAt": "2021-03-30 17:19:32.639",
    "handle": 1257,
    "name": "Keith Jones",
    "type": "Trainer",
    "isAssistant": 3,
    "teamId": 1610612745
  },
  {
    "id": 202431,
    "createdAt": "2021-03-30 17:18:05.934",
    "updatedAt": "2021-03-30 17:19:32.645",
    "handle": 202431,
    "name": "Jason Biles",
    "type": "Trainer",
    "isAssistant": 3,
    "teamId": 1610612745
  },
  {
    "id": 203785,
    "createdAt": "2021-03-30 17:18:05.936",
    "updatedAt": "2021-03-30 17:19:32.843",
    "handle": 203785,
    "name": "Greg Foster",
    "type": "Assistant Coach",
    "isAssistant": 2,
    "teamId": 1610612754
  },
  {
    "id": 203764,
    "createdAt": "2021-03-30 17:18:05.94",
    "updatedAt": "2021-03-30 17:19:32.883",
    "handle": 203764,
    "name": "Tyler Marsh",
    "type": "Assistant Coach",
    "isAssistant": 2,
    "teamId": 1610612754
  },
  {
    "id": 1271,
    "createdAt": "2021-03-30 17:18:05.943",
    "updatedAt": "2021-03-30 17:19:33.138",
    "handle": 1271,
    "name": "Larry Drew",
    "type": "Assistant Coach",
    "isAssistant": 2,
    "teamId": 1610612746
  },
  {
    "id": 2010,
    "createdAt": "2021-03-30 17:18:05.945",
    "updatedAt": "2021-03-30 17:19:33.153",
    "handle": 2010,
    "name": "Jasen Powell",
    "type": "Trainer",
    "isAssistant": 3,
    "teamId": 1610612746
  },
  {
    "id": 203797,
    "createdAt": "2021-03-30 17:18:05.947",
    "updatedAt": "2021-03-30 17:19:33.658",
    "handle": 203797,
    "name": "Brad Jones",
    "type": "Assistant Coach",
    "isAssistant": 2,
    "teamId": 1610612763
  },
  {
    "id": 204011,
    "createdAt": "2021-03-30 17:18:05.949",
    "updatedAt": "2021-03-30 17:19:33.683",
    "handle": 204011,
    "name": "Darko Rajakovic",
    "type": "Assistant Coach",
    "isAssistant": 2,
    "teamId": 1610612763
  },
  {
    "id": 204229,
    "createdAt": "2021-03-30 17:18:05.726",
    "updatedAt": "2021-03-30 17:19:33.899",
    "handle": 204229,
    "name": "Malik Allen",
    "type": "Assistant Coach",
    "isAssistant": 2,
    "teamId": 1610612748
  },
  {
    "id": 2406,
    "createdAt": "2021-03-30 17:18:05.951",
    "updatedAt": "2021-03-30 17:19:33.906",
    "handle": 2406,
    "name": "Caron Butler",
    "type": "Assistant Coach",
    "isAssistant": 2,
    "teamId": 1610612748
  },
  {
    "id": 1281,
    "createdAt": "2021-03-30 17:18:05.73",
    "updatedAt": "2021-03-30 17:19:33.946",
    "handle": 1281,
    "name": "Jay Sabol",
    "type": "Trainer",
    "isAssistant": 3,
    "teamId": 1610612748
  },
  {
    "id": 1628784,
    "createdAt": "2021-03-30 17:18:05.732",
    "updatedAt": "2021-03-30 17:19:34.14",
    "handle": 1628784,
    "name": "Pat St. Andrews",
    "type": "Assistant Coach",
    "isAssistant": 2,
    "teamId": 1610612749
  },
  {
    "id": 2649,
    "createdAt": "2021-03-30 17:18:05.734",
    "updatedAt": "2021-03-30 17:19:34.146",
    "handle": 2649,
    "name": "Chad Forcier",
    "type": "Assistant Coach",
    "isAssistant": 2,
    "teamId": 1610612749
  },
  {
    "id": 203005,
    "createdAt": "2021-03-30 17:18:05.737",
    "updatedAt": "2021-03-30 17:19:34.153",
    "handle": 203005,
    "name": "Darvin Ham",
    "type": "Assistant Coach",
    "isAssistant": 2,
    "teamId": 1610612749
  },
  {
    "id": 204224,
    "createdAt": "2021-03-30 17:18:05.953",
    "updatedAt": "2021-03-30 17:19:34.177",
    "handle": 204224,
    "name": "Ben Sullivan",
    "type": "Assistant Coach",
    "isAssistant": 2,
    "teamId": 1610612749
  },
  {
    "id": 204225,
    "createdAt": "2021-03-30 17:18:05.955",
    "updatedAt": "2021-03-30 17:19:34.185",
    "handle": 204225,
    "name": "Charles Lee",
    "type": "Assistant Coach",
    "isAssistant": 2,
    "teamId": 1610612749
  },
  {
    "id": 452,
    "createdAt": "2021-03-30 17:18:05.973",
    "updatedAt": "2021-03-30 17:19:34.193",
    "handle": 452,
    "name": "Vin Baker",
    "type": "Assistant Coach",
    "isAssistant": 2,
    "teamId": 1610612749
  },
  {
    "id": 202896,
    "createdAt": "2021-03-30 17:18:05.741",
    "updatedAt": "2021-03-30 17:19:34.391",
    "handle": 202896,
    "name": "Chris Finch",
    "type": "Head Coach",
    "isAssistant": 1,
    "teamId": 1610612750
  },
  {
    "id": 203150,
    "createdAt": "2021-03-30 17:18:05.744",
    "updatedAt": "2021-03-30 17:19:34.398",
    "handle": 203150,
    "name": "David Vanterpool",
    "type": "Associate Head Coach",
    "isAssistant": 9,
    "teamId": 1610612750
  },
  {
    "id": 1628772,
    "createdAt": "2021-03-30 17:18:05.746",
    "updatedAt": "2021-03-30 17:19:34.404",
    "handle": 1628772,
    "name": "Kevin Burleson",
    "type": "Assistant Coach",
    "isAssistant": 2,
    "teamId": 1610612750
  },
  {
    "id": 974,
    "createdAt": "2021-03-30 17:18:05.748",
    "updatedAt": "2021-03-30 17:19:34.428",
    "handle": 974,
    "name": "Joseph Blair",
    "type": "Assistant Coach",
    "isAssistant": 2,
    "teamId": 1610612750
  },
  {
    "id": 2146,
    "createdAt": "2021-03-30 17:18:05.752",
    "updatedAt": "2021-03-30 17:19:34.45",
    "handle": 2146,
    "name": "Gregg Farnam",
    "type": "Trainer",
    "isAssistant": 3,
    "teamId": 1610612750
  },
  {
    "id": 1277,
    "createdAt": "2021-03-30 17:18:05.976",
    "updatedAt": "2021-03-30 17:19:34.638",
    "handle": 1277,
    "name": "Stan Van Gundy",
    "type": "Head Coach",
    "isAssistant": 1,
    "teamId": 1610612740
  },
  {
    "id": 201676,
    "createdAt": "2021-03-30 17:18:05.978",
    "updatedAt": "2021-03-30 17:19:34.645",
    "handle": 201676,
    "name": "Fred Vinson",
    "type": "Assistant Coach",
    "isAssistant": 2,
    "teamId": 1610612740
  },
  {
    "id": 100101,
    "createdAt": "2021-03-30 17:18:05.979",
    "updatedAt": "2021-03-30 17:19:34.676",
    "handle": 100101,
    "name": "Teresa Weatherspoon",
    "type": "Assistant Coach",
    "isAssistant": 2,
    "teamId": 1610612740
  },
  {
    "id": 203243,
    "createdAt": "2021-03-30 17:18:05.754",
    "updatedAt": "2021-03-30 17:19:34.686",
    "handle": 203243,
    "name": "Casey Hill",
    "type": "Assistant Coach",
    "isAssistant": 2,
    "teamId": 1610612740
  },
  {
    "id": 777,
    "createdAt": "2021-03-30 17:18:05.981",
    "updatedAt": "2021-03-30 17:19:34.693",
    "handle": 777,
    "name": "Rex Walters",
    "type": "Assistant Coach",
    "isAssistant": 2,
    "teamId": 1610612740
  },
  {
    "id": 1630382,
    "createdAt": "2021-03-30 17:18:05.983",
    "updatedAt": "2021-03-30 17:19:34.7",
    "handle": 1630382,
    "name": "Tom Maystadt",
    "type": "Trainer",
    "isAssistant": 3,
    "teamId": 1610612740
  },
  {
    "id": 204008,
    "createdAt": "2021-03-30 17:18:05.775",
    "updatedAt": "2021-03-30 17:19:34.903",
    "handle": 204008,
    "name": "Johnnie Bryant",
    "type": "Associate Head Coach",
    "isAssistant": 9,
    "teamId": 1610612752
  },
  {
    "id": 1630161,
    "createdAt": "2021-03-30 17:18:05.777",
    "updatedAt": "2021-03-30 17:19:34.928",
    "handle": 1630161,
    "name": "Kenny Payne",
    "type": "Lead Assistant Coach",
    "isAssistant": 13,
    "teamId": 1610612752
  },
  {
    "id": 1285,
    "createdAt": "2021-03-30 17:18:05.985",
    "updatedAt": "2021-03-30 17:19:34.936",
    "handle": 1285,
    "name": "Mike Woodson",
    "type": "Assistant Coach",
    "isAssistant": 2,
    "teamId": 1610612752
  },
  {
    "id": 2519,
    "createdAt": "2021-03-30 17:18:05.78",
    "updatedAt": "2021-03-30 17:19:34.958",
    "handle": 2519,
    "name": "Andy Greer",
    "type": "Assistant Coach",
    "isAssistant": 2,
    "teamId": 1610612752
  },
  {
    "id": 101269,
    "createdAt": "2021-03-30 17:18:05.782",
    "updatedAt": "2021-03-30 17:19:34.982",
    "handle": 101269,
    "name": "Anthony Goenaga",
    "type": "Trainer",
    "isAssistant": 3,
    "teamId": 1610612752
  },
  {
    "id": 1627327,
    "createdAt": "2021-03-30 17:18:05.784",
    "updatedAt": "2021-03-30 17:19:35.185",
    "handle": 1627327,
    "name": "Mark Daigneault",
    "type": "Head Coach",
    "isAssistant": 1,
    "teamId": 1610612760
  },
  {
    "id": 1629423,
    "createdAt": "2021-03-30 17:18:05.788",
    "updatedAt": "2021-03-30 17:19:35.246",
    "handle": 1629423,
    "name": "Donnie Strack",
    "type": "Trainer",
    "isAssistant": 3,
    "teamId": 1610612760
  },
  {
    "id": 2168,
    "createdAt": "2021-03-30 17:18:05.791",
    "updatedAt": "2021-03-30 17:19:35.437",
    "handle": 2168,
    "name": "Steve Clifford",
    "type": "Head Coach",
    "isAssistant": 1,
    "teamId": 1610612753
  },
  {
    "id": 1627341,
    "createdAt": "2021-03-30 17:18:05.987",
    "updatedAt": "2021-03-30 17:19:35.443",
    "handle": 1627341,
    "name": "Mike Batiste",
    "type": "Assistant Coach",
    "isAssistant": 2,
    "teamId": 1610612753
  },
  {
    "id": 2821,
    "createdAt": "2021-03-30 17:18:05.793",
    "updatedAt": "2021-03-30 17:19:35.449",
    "handle": 2821,
    "name": "Ty Corbin",
    "type": "Assistant Coach",
    "isAssistant": 2,
    "teamId": 1610612753
  },
  {
    "id": 204004,
    "createdAt": "2021-03-30 17:18:05.795",
    "updatedAt": "2021-03-30 17:19:35.455",
    "handle": 204004,
    "name": "Steve Hetzel",
    "type": "Assistant Coach",
    "isAssistant": 2,
    "teamId": 1610612753
  },
  {
    "id": 2720,
    "createdAt": "2021-03-30 17:18:05.797",
    "updatedAt": "2021-03-30 17:19:35.504",
    "handle": 2720,
    "name": "Ernest Eugene",
    "type": "Trainer",
    "isAssistant": 3,
    "teamId": 1610612753
  },
  {
    "id": 2515,
    "createdAt": "2021-03-30 17:18:05.798",
    "updatedAt": "2021-03-30 17:19:35.737",
    "handle": 2515,
    "name": "Dan Burke",
    "type": "Assistant Coach",
    "isAssistant": 2,
    "teamId": 1610612755
  },
  {
    "id": 202108,
    "createdAt": "2021-03-30 17:18:05.8",
    "updatedAt": "2021-03-30 17:19:35.744",
    "handle": 202108,
    "name": "Sam Cassell",
    "type": "Assistant Coach",
    "isAssistant": 2,
    "teamId": 1610612755
  },
  {
    "id": 202434,
    "createdAt": "2021-03-30 17:18:05.802",
    "updatedAt": "2021-03-30 17:19:35.751",
    "handle": 202434,
    "name": "Popeye Jones",
    "type": "Assistant Coach",
    "isAssistant": 2,
    "teamId": 1610612755
  },
  {
    "id": 201220,
    "createdAt": "2021-03-30 17:18:05.804",
    "updatedAt": "2021-03-30 17:19:35.757",
    "handle": 201220,
    "name": "David Joerger",
    "type": "Assistant Coach",
    "isAssistant": 2,
    "teamId": 1610612755
  },
  {
    "id": 1360,
    "createdAt": "2021-03-30 17:18:05.824",
    "updatedAt": "2021-03-30 17:19:35.78",
    "handle": 1360,
    "name": "Kevin Johnson",
    "type": "Trainer",
    "isAssistant": 3,
    "teamId": 1610612755
  },
  {
    "id": 101273,
    "createdAt": "2021-03-30 17:18:05.826",
    "updatedAt": "2021-03-30 17:19:35.953",
    "handle": 101273,
    "name": "Monty Williams",
    "type": "Head Coach",
    "isAssistant": 1,
    "teamId": 1610612756
  },
  {
    "id": 202111,
    "createdAt": "2021-03-30 17:18:05.827",
    "updatedAt": "2021-03-30 17:19:35.992",
    "handle": 202111,
    "name": "Kevin Young",
    "type": "Assistant Coach",
    "isAssistant": 2,
    "teamId": 1610612756
  },
  {
    "id": 1337,
    "createdAt": "2021-03-30 17:18:05.829",
    "updatedAt": "2021-03-30 17:19:36.193",
    "handle": 1337,
    "name": "Terry Stotts",
    "type": "Head Coach",
    "isAssistant": 1,
    "teamId": 1610612757
  },
  {
    "id": 203170,
    "createdAt": "2021-03-30 17:18:05.831",
    "updatedAt": "2021-03-30 17:19:36.234",
    "handle": 203170,
    "name": "Dale Osbourne",
    "type": "Assistant Coach",
    "isAssistant": 2,
    "teamId": 1610612757
  },
  {
    "id": 2457,
    "createdAt": "2021-03-30 17:18:05.833",
    "updatedAt": "2021-03-30 17:19:36.248",
    "handle": 2457,
    "name": "Jannero Pargo",
    "type": "Assistant Coach",
    "isAssistant": 2,
    "teamId": 1610612757
  },
  {
    "id": 101272,
    "createdAt": "2021-03-30 17:18:05.835",
    "updatedAt": "2021-03-30 17:19:36.254",
    "handle": 101272,
    "name": "Geoff Clark",
    "type": "Trainer",
    "isAssistant": 3,
    "teamId": 1610612757
  },
  {
    "id": 1243,
    "createdAt": "2021-03-30 17:18:05.837",
    "updatedAt": "2021-03-30 17:19:36.487",
    "handle": 1243,
    "name": "Alvin Gentry",
    "type": "Associate Head Coach",
    "isAssistant": 9,
    "teamId": 1610612758
  },
  {
    "id": 1629711,
    "createdAt": "2021-03-30 17:18:05.841",
    "updatedAt": "2021-03-30 17:19:36.494",
    "handle": 1629711,
    "name": "Roy Rana",
    "type": "Assistant Coach",
    "isAssistant": 2,
    "teamId": 1610612758
  },
  {
    "id": 1627331,
    "createdAt": "2021-03-30 17:18:05.843",
    "updatedAt": "2021-03-30 17:19:36.576",
    "handle": 1627331,
    "name": "Will Scott",
    "type": "Assistant Coach for Player Development",
    "isAssistant": 12,
    "teamId": 1610612758
  },
  {
    "id": 203167,
    "createdAt": "2021-03-30 17:18:05.845",
    "updatedAt": "2021-03-30 17:19:36.592",
    "handle": 203167,
    "name": "Joe Resendez",
    "type": "Trainer",
    "isAssistant": 3,
    "teamId": 1610612758
  },
  {
    "id": 873,
    "createdAt": "2021-03-30 17:18:05.847",
    "updatedAt": "2021-03-30 17:19:36.793",
    "handle": 873,
    "name": "Gregg Popovich",
    "type": "Head Coach",
    "isAssistant": 1,
    "teamId": 1610612759
  },
  {
    "id": 1628188,
    "createdAt": "2021-03-30 17:18:05.849",
    "updatedAt": "2021-03-30 17:19:36.8",
    "handle": 1628188,
    "name": "Mitch Johnson",
    "type": "Assistant Coach",
    "isAssistant": 2,
    "teamId": 1610612759
  },
  {
    "id": 2887,
    "createdAt": "2021-03-30 17:18:05.854",
    "updatedAt": "2021-03-30 17:19:36.832",
    "handle": 2887,
    "name": "Chip Engelland",
    "type": "Assistant Coach",
    "isAssistant": 2,
    "teamId": 1610612759
  },
  {
    "id": 203606,
    "createdAt": "2021-03-30 17:18:05.873",
    "updatedAt": "2021-03-30 17:19:37.038",
    "handle": 203606,
    "name": "Nick Nurse",
    "type": "Head Coach",
    "isAssistant": 1,
    "teamId": 1610612761
  },
  {
    "id": 1629821,
    "createdAt": "2021-03-30 17:18:05.875",
    "updatedAt": "2021-03-30 17:19:37.045",
    "handle": 1629821,
    "name": "Jon Goodwillie",
    "type": "Assistant Coach",
    "isAssistant": 2,
    "teamId": 1610612761
  },
  {
    "id": 203604,
    "createdAt": "2021-03-30 17:18:05.877",
    "updatedAt": "2021-03-30 17:19:37.051",
    "handle": 203604,
    "name": "Jama Mahlalela",
    "type": "Assistant Coach",
    "isAssistant": 2,
    "teamId": 1610612761
  },
  {
    "id": 1356,
    "createdAt": "2021-03-30 17:18:05.879",
    "updatedAt": "2021-03-30 17:19:37.093",
    "handle": 1356,
    "name": "Scott McCullough",
    "type": "Trainer",
    "isAssistant": 3,
    "teamId": 1610612761
  },
  {
    "id": 202439,
    "createdAt": "2021-03-30 17:18:05.881",
    "updatedAt": "2021-03-30 17:19:37.289",
    "handle": 202439,
    "name": "Quin Snyder",
    "type": "Head Coach",
    "isAssistant": 1,
    "teamId": 1610612762
  },
  {
    "id": 1627328,
    "createdAt": "2021-03-30 17:18:05.885",
    "updatedAt": "2021-03-30 17:19:37.656",
    "handle": 1627328,
    "name": "Jarell Christian",
    "type": "Assistant Coach",
    "isAssistant": 2,
    "teamId": 1610612764
  },
  {
    "id": 1629412,
    "createdAt": "2021-03-30 17:18:06.097",
    "updatedAt": "2021-03-30 17:19:30.386",
    "handle": 1629412,
    "name": "Dan Liburd",
    "type": "Strength and Conditioning Coach",
    "isAssistant": 5,
    "teamId": 1610612751
  },
  {
    "id": 1778,
    "createdAt": "2021-03-30 17:18:06.084",
    "updatedAt": "2021-03-30 17:19:29.636",
    "handle": 1778,
    "name": "Nate McMillan",
    "type": "Head Coach",
    "isAssistant": 1,
    "teamId": 1610612737
  },
  {
    "id": 2607,
    "createdAt": "2021-03-30 17:18:05.886",
    "updatedAt": "2021-03-30 17:19:29.648",
    "handle": 2607,
    "name": "Chris Jent",
    "type": "Assistant Coach",
    "isAssistant": 2,
    "teamId": 1610612737
  },
  {
    "id": 2384,
    "createdAt": "2021-03-30 17:18:05.889",
    "updatedAt": "2021-03-30 17:19:29.657",
    "handle": 2384,
    "name": "Melvin Hunt",
    "type": "Assistant Coach",
    "isAssistant": 2,
    "teamId": 1610612737
  },
  {
    "id": 203753,
    "createdAt": "2021-03-30 17:18:05.496",
    "updatedAt": "2021-03-30 17:19:30.632",
    "handle": 203753,
    "name": "Ronald Nored",
    "type": "Assistant Coach",
    "isAssistant": 2,
    "teamId": 1610612766
  },
  {
    "id": 1630017,
    "createdAt": "2021-03-30 17:18:06.086",
    "updatedAt": "2021-03-30 17:19:29.705",
    "handle": 1630017,
    "name": "John Dusel",
    "type": "Assistant Trainer",
    "isAssistant": 4,
    "teamId": 1610612737
  },
  {
    "id": 202743,
    "createdAt": "2021-03-30 17:18:05.675",
    "updatedAt": "2021-03-30 17:19:30.936",
    "handle": 202743,
    "name": "John Bryant",
    "type": "Assistant Coach",
    "isAssistant": 2,
    "teamId": 1610612741
  },
  {
    "id": 203535,
    "createdAt": "2021-03-30 17:18:06.089",
    "updatedAt": "2021-03-30 17:19:29.941",
    "handle": 203535,
    "name": "Brad Stevens",
    "type": "Head Coach",
    "isAssistant": 1,
    "teamId": 1610612738
  },
  {
    "id": 1628807,
    "createdAt": "2021-03-30 17:18:05.455",
    "updatedAt": "2021-03-30 17:19:29.949",
    "handle": 1628807,
    "name": "Brandon Bailey",
    "type": "Assistant Coach",
    "isAssistant": 2,
    "teamId": 1610612738
  },
  {
    "id": 1627666,
    "createdAt": "2021-03-30 17:18:05.602",
    "updatedAt": "2021-03-30 17:19:32.351",
    "handle": 1627666,
    "name": "Chris DeMarco",
    "type": "Assistant Coach for Player Development",
    "isAssistant": 12,
    "teamId": 1610612744
  },
  {
    "id": 1627590,
    "createdAt": "2021-03-30 17:18:06.091",
    "updatedAt": "2021-03-30 17:19:29.989",
    "handle": 1627590,
    "name": "Jerome Allen",
    "type": "Assistant Coach",
    "isAssistant": 2,
    "teamId": 1610612738
  },
  {
    "id": 203168,
    "createdAt": "2021-03-30 17:18:05.48",
    "updatedAt": "2021-03-30 17:19:30.004",
    "handle": 203168,
    "name": "Jay Larranaga",
    "type": "Assistant Coach",
    "isAssistant": 2,
    "teamId": 1610612738
  },
  {
    "id": 2794,
    "createdAt": "2021-03-30 17:18:06.099",
    "updatedAt": "2021-03-30 17:19:31.186",
    "handle": 2794,
    "name": "JB Bickerstaff",
    "type": "Head Coach",
    "isAssistant": 1,
    "teamId": 1610612739
  },
  {
    "id": 1628179,
    "createdAt": "2021-03-30 17:18:06.094",
    "updatedAt": "2021-03-30 17:19:30.335",
    "handle": 1628179,
    "name": "Royal Ivey",
    "type": "Assistant Coach",
    "isAssistant": 2,
    "teamId": 1610612751
  },
  {
    "id": 201168,
    "createdAt": "2021-03-30 17:18:05.901",
    "updatedAt": "2021-03-30 17:19:30.353",
    "handle": 201168,
    "name": "Tiago Splitter",
    "type": "Assistant Coach for Player Development",
    "isAssistant": 12,
    "teamId": 1610612751
  },
  {
    "id": 1335,
    "createdAt": "2021-03-30 17:18:06.102",
    "updatedAt": "2021-03-30 17:19:32.041",
    "handle": 1335,
    "name": "Dwane Casey",
    "type": "Head Coach",
    "isAssistant": 1,
    "teamId": 1610612765
  },
  {
    "id": 202565,
    "createdAt": "2021-03-30 17:18:05.538",
    "updatedAt": "2021-03-30 17:19:31.241",
    "handle": 202565,
    "name": "Mike Gerrity",
    "type": "Assistant Coach",
    "isAssistant": 2,
    "teamId": 1610612739
  },
  {
    "id": 204085,
    "createdAt": "2021-03-30 17:18:05.588",
    "updatedAt": "2021-03-30 17:19:32.086",
    "handle": 204085,
    "name": "Sean Sweeney",
    "type": "Assistant Coach",
    "isAssistant": 2,
    "teamId": 1610612765
  },
  {
    "id": 202599,
    "createdAt": "2021-03-30 17:18:06.1",
    "updatedAt": "2021-03-30 17:19:31.5",
    "handle": 202599,
    "name": "Darrell Armstrong",
    "type": "Assistant Coach",
    "isAssistant": 2,
    "teamId": 1610612742
  },
  {
    "id": 1628782,
    "createdAt": "2021-03-30 17:18:05.546",
    "updatedAt": "2021-03-30 17:19:31.507",
    "handle": 1628782,
    "name": "Mike Weinar",
    "type": "Assistant Coach",
    "isAssistant": 2,
    "teamId": 1610612742
  },
  {
    "id": 203600,
    "createdAt": "2021-03-30 17:18:05.575",
    "updatedAt": "2021-03-30 17:19:31.796",
    "handle": 203600,
    "name": "David Adelman",
    "type": "Assistant Coach",
    "isAssistant": 2,
    "teamId": 1610612743
  },
  {
    "id": 1497,
    "createdAt": "2021-03-30 17:18:06.127",
    "updatedAt": "2021-03-30 17:19:33.094",
    "handle": 1497,
    "name": "Chauncey Billups",
    "type": "Lead Assistant Coach",
    "isAssistant": 13,
    "teamId": 1610612746
  },
  {
    "id": 204005,
    "createdAt": "2021-03-30 17:18:06.104",
    "updatedAt": "2021-03-30 17:19:32.295",
    "handle": 204005,
    "name": "Steve Kerr",
    "type": "Head Coach",
    "isAssistant": 1,
    "teamId": 1610612744
  },
  {
    "id": 2205,
    "createdAt": "2021-03-30 17:18:06.123",
    "updatedAt": "2021-03-30 17:19:32.599",
    "handle": 2205,
    "name": "DeSagana Diop",
    "type": "Assistant Coach",
    "isAssistant": 2,
    "teamId": 1610612745
  },
  {
    "id": 384,
    "createdAt": "2021-03-30 17:18:05.938",
    "updatedAt": "2021-03-30 17:19:32.856",
    "handle": 384,
    "name": "Calbert Cheaney",
    "type": "Assistant Coach",
    "isAssistant": 2,
    "teamId": 1610612754
  },
  {
    "id": 203599,
    "createdAt": "2021-03-30 17:18:06.126",
    "updatedAt": "2021-03-30 17:19:33.087",
    "handle": 203599,
    "name": "Dan Craig",
    "type": "Associate Head Coach",
    "isAssistant": 9,
    "teamId": 1610612746
  },
  {
    "id": 1630361,
    "createdAt": "2021-03-30 17:18:06.129",
    "updatedAt": "2021-03-30 17:19:33.102",
    "handle": 1630361,
    "name": "Jeremy Castleberry",
    "type": "Assistant Coach",
    "isAssistant": 2,
    "teamId": 1610612746
  },
  {
    "id": 201689,
    "createdAt": "2021-03-30 17:18:06.131",
    "updatedAt": "2021-03-30 17:19:33.108",
    "handle": 201689,
    "name": "Roy Rogers",
    "type": "Assistant Coach",
    "isAssistant": 2,
    "teamId": 1610612746
  },
  {
    "id": 201690,
    "createdAt": "2021-03-30 17:18:06.133",
    "updatedAt": "2021-03-30 17:19:33.131",
    "handle": 201690,
    "name": "Kenny Atkinson",
    "type": "Assistant Coach",
    "isAssistant": 2,
    "teamId": 1610612746
  },
  {
    "id": 2814,
    "createdAt": "2021-03-30 17:18:05.685",
    "updatedAt": "2021-03-30 17:19:33.145",
    "handle": 2814,
    "name": "Brendan O'Connor",
    "type": "Assistant Coach",
    "isAssistant": 2,
    "teamId": 1610612746
  },
  {
    "id": 2130,
    "createdAt": "2021-03-30 17:18:05.697",
    "updatedAt": "2021-03-30 17:19:33.408",
    "handle": 2130,
    "name": "Mike Penberthy",
    "type": "Assistant Coach",
    "isAssistant": 2,
    "teamId": 1610612747
  },
  {
    "id": 1628472,
    "createdAt": "2021-03-30 17:18:06.135",
    "updatedAt": "2021-03-30 17:19:33.402",
    "handle": 1628472,
    "name": "Miles Simon",
    "type": "Assistant Coach",
    "isAssistant": 2,
    "teamId": 1610612747
  },
  {
    "id": 204226,
    "createdAt": "2021-03-30 17:18:05.728",
    "updatedAt": "2021-03-30 17:19:33.931",
    "handle": 204226,
    "name": "Chris Quinn",
    "type": "Assistant Coach",
    "isAssistant": 2,
    "teamId": 1610612748
  },
  {
    "id": 201766,
    "createdAt": "2021-03-30 17:18:06.136",
    "updatedAt": "2021-03-30 17:19:33.432",
    "handle": 201766,
    "name": "Nina Hsieh",
    "type": "Trainer",
    "isAssistant": 3,
    "teamId": 1610612747
  },
  {
    "id": 1630290,
    "createdAt": "2021-03-30 17:18:06.139",
    "updatedAt": "2021-03-30 17:19:33.638",
    "handle": 1630290,
    "name": "Sonia Raman",
    "type": "Assistant Coach",
    "isAssistant": 2,
    "teamId": 1610612763
  },
  {
    "id": 202433,
    "createdAt": "2021-03-30 17:18:06.141",
    "updatedAt": "2021-03-30 17:19:33.645",
    "handle": 202433,
    "name": "Vitaly Potapenko",
    "type": "Assistant Coach",
    "isAssistant": 2,
    "teamId": 1610612763
  },
  {
    "id": 201336,
    "createdAt": "2021-03-30 17:18:06.143",
    "updatedAt": "2021-03-30 17:19:33.697",
    "handle": 201336,
    "name": "Blake Ahearn",
    "type": "Assistant Coach",
    "isAssistant": 2,
    "teamId": 1610612763
  },
  {
    "id": 201682,
    "createdAt": "2021-03-30 17:18:06.144",
    "updatedAt": "2021-03-30 17:19:33.939",
    "handle": 201682,
    "name": "Octavio De La Grana",
    "type": "Assistant Coach for Player Development",
    "isAssistant": 12,
    "teamId": 1610612748
  },
  {
    "id": 1371,
    "createdAt": "2021-03-30 17:18:06.146",
    "updatedAt": "2021-03-30 17:19:34.134",
    "handle": 1371,
    "name": "Mike Budenholzer",
    "type": "Head Coach",
    "isAssistant": 1,
    "teamId": 1610612749
  },
  {
    "id": 201692,
    "createdAt": "2021-03-30 17:18:05.739",
    "updatedAt": "2021-03-30 17:19:34.2",
    "handle": 201692,
    "name": "Scott Faust",
    "type": "Trainer",
    "isAssistant": 3,
    "teamId": 1610612749
  },
  {
    "id": 202109,
    "createdAt": "2021-03-30 17:18:05.75",
    "updatedAt": "2021-03-30 17:19:34.443",
    "handle": 202109,
    "name": "Bryan Gates",
    "type": "Assistant Coach",
    "isAssistant": 2,
    "teamId": 1610612750
  },
  {
    "id": 203143,
    "createdAt": "2021-03-30 17:18:06.148",
    "updatedAt": "2021-03-30 17:19:34.436",
    "handle": 203143,
    "name": "Pablo Prigioni",
    "type": "Assistant Coach",
    "isAssistant": 2,
    "teamId": 1610612750
  },
  {
    "id": 1301,
    "createdAt": "2021-03-30 17:18:05.773",
    "updatedAt": "2021-03-30 17:19:34.895",
    "handle": 1301,
    "name": "Tom Thibodeau",
    "type": "Head Coach",
    "isAssistant": 1,
    "teamId": 1610612752
  },
  {
    "id": 1629432,
    "createdAt": "2021-03-30 17:18:06.15",
    "updatedAt": "2021-03-30 17:19:34.707",
    "handle": 1629432,
    "name": "Todd Campbell",
    "type": "Assistant Trainer",
    "isAssistant": 4,
    "teamId": 1610612740
  },
  {
    "id": 1941,
    "createdAt": "2021-03-30 17:18:06.154",
    "updatedAt": "2021-03-30 17:19:35.706",
    "handle": 1941,
    "name": "Doc Rivers",
    "type": "Head Coach",
    "isAssistant": 1,
    "teamId": 1610612755
  },
  {
    "id": 101173,
    "createdAt": "2021-03-30 17:18:05.995",
    "updatedAt": "2021-03-30 17:19:36.006",
    "handle": 101173,
    "name": "Mark Bryant",
    "type": "Assistant Coach",
    "isAssistant": 2,
    "teamId": 1610612756
  },
  {
    "id": 1629410,
    "createdAt": "2021-03-30 17:18:06.172",
    "updatedAt": "2021-03-30 17:19:36.03",
    "handle": 1629410,
    "name": "David Crewe",
    "type": "Trainer",
    "isAssistant": 3,
    "teamId": 1610612756
  },
  {
    "id": 202891,
    "createdAt": "2021-03-30 17:18:06.175",
    "updatedAt": "2021-03-30 17:19:36.2",
    "handle": 202891,
    "name": "Nate Tibbetts",
    "type": "Associate Head Coach",
    "isAssistant": 9,
    "teamId": 1610612757
  },
  {
    "id": 1628240,
    "createdAt": "2021-03-30 17:18:05.997",
    "updatedAt": "2021-03-30 17:19:36.207",
    "handle": 1628240,
    "name": "John McCullough",
    "type": "Assistant Coach",
    "isAssistant": 2,
    "teamId": 1610612757
  },
  {
    "id": 1627471,
    "createdAt": "2021-03-30 17:18:06",
    "updatedAt": "2021-03-30 17:19:36.241",
    "handle": 1627471,
    "name": "Jim Moran",
    "type": "Assistant Coach",
    "isAssistant": 2,
    "teamId": 1610612757
  },
  {
    "id": 204012,
    "createdAt": "2021-03-30 17:18:06.002",
    "updatedAt": "2021-03-30 17:19:36.478",
    "handle": 204012,
    "name": "Luke Walton",
    "type": "Head Coach",
    "isAssistant": 1,
    "teamId": 1610612758
  },
  {
    "id": 202985,
    "createdAt": "2021-03-30 17:18:06.023",
    "updatedAt": "2021-03-30 17:19:36.544",
    "handle": 202985,
    "name": "Bobby Jackson",
    "type": "Assistant Coach for Player Development",
    "isAssistant": 12,
    "teamId": 1610612758
  },
  {
    "id": 1627971,
    "createdAt": "2021-03-30 17:18:06.177",
    "updatedAt": "2021-03-30 17:19:36.585",
    "handle": 1627971,
    "name": "Rico Hines",
    "type": "Assistant Coach for Player Development",
    "isAssistant": 12,
    "teamId": 1610612758
  },
  {
    "id": 204019,
    "createdAt": "2021-03-30 17:18:06.026",
    "updatedAt": "2021-03-30 17:19:36.839",
    "handle": 204019,
    "name": "Becky Hammon",
    "type": "Assistant Coach",
    "isAssistant": 2,
    "teamId": 1610612759
  },
  {
    "id": 1628181,
    "createdAt": "2021-03-30 17:18:06.027",
    "updatedAt": "2021-03-30 17:19:36.846",
    "handle": 1628181,
    "name": "Will Hardy",
    "type": "Assistant Coach",
    "isAssistant": 2,
    "teamId": 1610612759
  },
  {
    "id": 1264,
    "createdAt": "2021-03-30 17:18:06.029",
    "updatedAt": "2021-03-30 17:19:36.853",
    "handle": 1264,
    "name": "Will Sevening",
    "type": "Trainer",
    "isAssistant": 3,
    "teamId": 1610612759
  },
  {
    "id": 1629761,
    "createdAt": "2021-03-30 17:18:06.031",
    "updatedAt": "2021-03-30 17:19:37.08",
    "handle": 1629761,
    "name": "Fab Flournoy",
    "type": "Assistant Coach",
    "isAssistant": 2,
    "teamId": 1610612761
  },
  {
    "id": 201878,
    "createdAt": "2021-03-30 17:18:06.033",
    "updatedAt": "2021-03-30 17:19:37.087",
    "handle": 201878,
    "name": "Adrian Griffin",
    "type": "Assistant Coach",
    "isAssistant": 2,
    "teamId": 1610612761
  },
  {
    "id": 1630282,
    "createdAt": "2021-03-30 17:18:06.035",
    "updatedAt": "2021-03-30 17:19:37.296",
    "handle": 1630282,
    "name": "Sergi Oliva",
    "type": "Assistant Coach",
    "isAssistant": 2,
    "teamId": 1610612762
  },
  {
    "id": 2039,
    "createdAt": "2021-03-30 17:18:06.036",
    "updatedAt": "2021-03-30 17:19:37.302",
    "handle": 2039,
    "name": "Keyon Dooling",
    "type": "Assistant Coach",
    "isAssistant": 2,
    "teamId": 1610612762
  },
  {
    "id": 725,
    "createdAt": "2021-03-30 17:18:06.038",
    "updatedAt": "2021-03-30 17:19:37.326",
    "handle": 725,
    "name": "Dell Demps",
    "type": "Assistant Coach",
    "isAssistant": 2,
    "teamId": 1610612762
  },
  {
    "id": 204007,
    "createdAt": "2021-03-30 17:18:06.041",
    "updatedAt": "2021-03-30 17:19:37.333",
    "handle": 204007,
    "name": "Alex Jensen",
    "type": "Assistant Coach",
    "isAssistant": 2,
    "teamId": 1610612762
  },
  {
    "id": 1628216,
    "createdAt": "2021-03-30 17:18:06.045",
    "updatedAt": "2021-03-30 17:19:37.346",
    "handle": 1628216,
    "name": "Bryan Bailey",
    "type": "Assistant Coach",
    "isAssistant": 2,
    "teamId": 1610612762
  },
  {
    "id": 1630280,
    "createdAt": "2021-03-30 17:18:06.18",
    "updatedAt": "2021-03-30 17:19:37.352",
    "handle": 1630280,
    "name": "Vince Legarza",
    "type": "Assistant Coach",
    "isAssistant": 2,
    "teamId": 1610612762
  },
  {
    "id": 1630281,
    "createdAt": "2021-03-30 17:18:06.047",
    "updatedAt": "2021-03-30 17:19:37.358",
    "handle": 1630281,
    "name": "Lamar Skeeter",
    "type": "Assistant Coach",
    "isAssistant": 2,
    "teamId": 1610612762
  },
  {
    "id": 1997,
    "createdAt": "2021-03-30 17:18:06.049",
    "updatedAt": "2021-03-30 17:19:37.38",
    "handle": 1997,
    "name": "Mike Wells",
    "type": "Assistant Coach",
    "isAssistant": 2,
    "teamId": 1610612762
  },
  {
    "id": 101277,
    "createdAt": "2021-03-30 17:18:06.051",
    "updatedAt": "2021-03-30 17:19:37.394",
    "handle": 101277,
    "name": "Brian Zettler",
    "type": "Trainer",
    "isAssistant": 3,
    "teamId": 1610612762
  },
  {
    "id": 1655,
    "createdAt": "2021-03-30 17:18:06.054",
    "updatedAt": "2021-03-30 17:19:37.604",
    "handle": 1655,
    "name": "Tony Brown",
    "type": "Associate Head Coach",
    "isAssistant": 9,
    "teamId": 1610612764
  },
  {
    "id": 1630364,
    "createdAt": "2021-03-30 17:18:06.074",
    "updatedAt": "2021-03-30 17:19:37.628",
    "handle": 1630364,
    "name": "David Atkins",
    "type": "Assistant Coach",
    "isAssistant": 2,
    "teamId": 1610612764
  },
  {
    "id": 201665,
    "createdAt": "2021-03-30 17:18:06.077",
    "updatedAt": "2021-03-30 17:19:37.635",
    "handle": 201665,
    "name": "MIke Longabardi",
    "type": "Assistant Coach",
    "isAssistant": 2,
    "teamId": 1610612764
  },
  {
    "id": 202105,
    "createdAt": "2021-03-30 17:18:06.08",
    "updatedAt": "2021-03-30 17:19:37.642",
    "handle": 202105,
    "name": "Robert Pack",
    "type": "Assistant Coach",
    "isAssistant": 2,
    "teamId": 1610612764
  },
  {
    "id": 203601,
    "createdAt": "2021-03-30 17:18:06.182",
    "updatedAt": "2021-03-30 17:19:37.649",
    "handle": 203601,
    "name": "Mike Terpstra",
    "type": "Assistant Coach",
    "isAssistant": 2,
    "teamId": 1610612764
  },
  {
    "id": 200744,
    "createdAt": "2021-03-30 17:18:06.184",
    "updatedAt": "2021-03-30 17:19:37.69",
    "handle": 200744,
    "name": "Corey Gaines",
    "type": "Assistant Coach",
    "isAssistant": 2,
    "teamId": 1610612764
  },
  {
    "id": 203375,
    "createdAt": "2021-03-30 17:18:05.631",
    "updatedAt": "2021-03-30 17:19:34.943",
    "handle": 203375,
    "name": "Darren Erman",
    "type": "Assistant Coach",
    "isAssistant": 2,
    "teamId": 1610612752
  },
  {
    "id": 1628178,
    "createdAt": "2021-03-30 17:18:05.786",
    "updatedAt": "2021-03-30 17:19:35.232",
    "handle": 1628178,
    "name": "Vin Bhavnani",
    "type": "Assistant Coach",
    "isAssistant": 2,
    "teamId": 1610612760
  },
  {
    "id": 1627164,
    "createdAt": "2021-03-30 17:18:05.989",
    "updatedAt": "2021-03-30 17:19:35.49",
    "handle": 1627164,
    "name": "Bruce Kreutzer",
    "type": "Assistant Coach",
    "isAssistant": 2,
    "teamId": 1610612753
  },
  {
    "id": 1627336,
    "createdAt": "2021-03-30 17:18:06.152",
    "updatedAt": "2021-03-30 17:19:35.497",
    "handle": 1627336,
    "name": "Dylan Murphy",
    "type": "Assistant Coach",
    "isAssistant": 2,
    "teamId": 1610612753
  },
  {
    "id": 1629169,
    "createdAt": "2021-03-30 17:18:05.646",
    "updatedAt": "2021-03-30 17:19:35.73",
    "handle": 1629169,
    "name": "Brian Adams",
    "type": "Assistant Coach",
    "isAssistant": 2,
    "teamId": 1610612755
  },
  {
    "id": 1628228,
    "createdAt": "2021-03-30 17:18:05.992",
    "updatedAt": "2021-03-30 17:19:35.999",
    "handle": 1628228,
    "name": "Willie Green",
    "type": "Assistant Coach",
    "isAssistant": 2,
    "teamId": 1610612756
  },
  {
    "id": 203605,
    "createdAt": "2021-03-30 17:18:06.004",
    "updatedAt": "2021-03-30 17:19:36.509",
    "handle": 203605,
    "name": "Jesse Mermuys",
    "type": "Assistant Coach",
    "isAssistant": 2,
    "teamId": 1610612758
  },
  {
    "id": 1672,
    "createdAt": "2021-03-30 17:18:05.839",
    "updatedAt": "2021-03-30 17:19:36.537",
    "handle": 1672,
    "name": "Rex Kalamian",
    "type": "Assistant Coach",
    "isAssistant": 2,
    "teamId": 1610612758
  },
  {
    "id": 278,
    "createdAt": "2021-03-30 17:18:05.673",
    "updatedAt": "2021-03-30 17:19:36.552",
    "handle": 278,
    "name": "Stacey Augmon",
    "type": "Assistant Coach for Player Development",
    "isAssistant": 12,
    "teamId": 1610612758
  },
  {
    "id": 2443,
    "createdAt": "2021-03-30 17:18:05.852",
    "updatedAt": "2021-03-30 17:19:36.808",
    "handle": 2443,
    "name": "Darius Songaila",
    "type": "Assistant Coach",
    "isAssistant": 2,
    "teamId": 1610612759
  },
  {
    "id": 1629144,
    "createdAt": "2021-03-30 17:18:06.179",
    "updatedAt": "2021-03-30 17:19:37.057",
    "handle": 1629144,
    "name": "Sergio Scariolo",
    "type": "Assistant Coach",
    "isAssistant": 2,
    "teamId": 1610612761
  },
  {
    "id": 1626233,
    "createdAt": "2021-03-30 17:18:06.043",
    "updatedAt": "2021-03-30 17:19:37.34",
    "handle": 1626233,
    "name": "Jeff Watkinson",
    "type": "Assistant Coach",
    "isAssistant": 2,
    "teamId": 1610612762
  },
  {
    "id": 101203,
    "createdAt": "2021-03-30 17:18:05.883",
    "updatedAt": "2021-03-30 17:19:37.387",
    "handle": 101203,
    "name": "Eric Waters",
    "type": "Trainer",
    "isAssistant": 3,
    "teamId": 1610612762
  },
  {
    "id": 2623,
    "createdAt": "2021-03-30 17:18:06.052",
    "updatedAt": "2021-03-30 17:19:37.595",
    "handle": 2623,
    "name": "Scott Brooks",
    "type": "Head Coach",
    "isAssistant": 1,
    "teamId": 1610612764
  },
  {
    "id": 1630363,
    "createdAt": "2021-03-30 17:18:06.082",
    "updatedAt": "2021-03-30 17:19:37.683",
    "handle": 1630363,
    "name": "Dean Oliver",
    "type": "Assistant Coach",
    "isAssistant": 2,
    "teamId": 1610612764
  }
]
